leap_bundle/__init__.py
leap_bundle/main.py
leap_bundle/commands/__init__.py
leap_bundle/commands/auth.py
leap_bundle/commands/cancel.py
leap_bundle/commands/config.py
leap_bundle/commands/create.py
leap_bundle/commands/download.py
leap_bundle/commands/list.py
leap_bundle/commands/resume.py
leap_bundle/commands/validate.py
leap_bundle/types/__init__.py
leap_bundle/types/create.py
leap_bundle/types/list.py
leap_bundle/utils/__init__.py
leap_bundle/utils/api_client.py
leap_bundle/utils/config.py
leap_bundle/utils/constant.py
leap_bundle/utils/exception.py
leap_bundle/utils/hash.py
leap_bundle/utils/manifest_download.py
leap_bundle/utils/request_download.py
leap_bundle/utils/s3_upload_manager.py
leap_bundle/utils/upload.py
leap_bundle/utils/validation.py
leap_bundle-0.8.0.dist-info/METADATA
leap_bundle-0.8.0.dist-info/WHEEL
leap_bundle-0.8.0.dist-info/entry_points.txt
leap_bundle-0.8.0.dist-info/RECORD
