Metadata-Version: 2.4
Name: leap-bundle
Version: 0.8.0
Summary: Command line tool to create model bundles or download GGUF models for Liquid Edge AI Platform (LEAP)
Project-URL: Homepage, https://leap.liquid.ai
Project-URL: Documentation, https://docs.liquid.ai/leap/leap-bundle/quick-start
Project-URL: CHANGELOG, https://docs.liquid.ai/leap/leap-bundle/changelog
Project-URL: License, https://www.liquid.ai/lfm-license
Author-email: Liquid AI <leap@liquid.ai>
Maintainer-email: Liren Tu <liren@liquid.ai>
License: LFM Open License v1.0
Keywords: ai,cli,edge-model,machine-learning
Classifier: Development Status :: 4 - Beta
Classifier: Environment :: Console
Classifier: Intended Audience :: Developers
Classifier: License :: Other/Proprietary License
Classifier: Operating System :: OS Independent
Classifier: Programming Language :: Python :: 3
Classifier: Programming Language :: Python :: 3 :: Only
Classifier: Programming Language :: Python :: 3.8
Classifier: Programming Language :: Python :: 3.9
Classifier: Programming Language :: Python :: 3.10
Classifier: Programming Language :: Python :: 3.11
Classifier: Programming Language :: Python :: 3.12
Classifier: Topic :: Scientific/Engineering :: Artificial Intelligence
Classifier: Topic :: Software Development :: Libraries :: Python Modules
Classifier: Topic :: System :: Software Distribution
Requires-Python: >=3.9
Requires-Dist: boto3>=1.40.26
Requires-Dist: pydantic>=2.11.7
Requires-Dist: pyyaml>=6.0.2
Requires-Dist: requests>=2.31.0
Requires-Dist: rich>=14.1.0
Requires-Dist: typer>=0.17.4
